{
  ":column-names": ["ID_GRUPO", "ID_KEYWORD", "COUNTRY_TERRITORY", "REGION", "STR_REGION",
    "Clicks", "Country", "Language", "Category", "CampaignName", "AdNetworkType2",
    "Date", "DayOfWeek", "Device", "MonthOfYear", "Keyword", "GoogleAdPosition",
    "MatchType", "Impressions"],
  ":rows": [
    {
      "ID_GRUPO" : 36874384791,
      "ID_KEYWORD" : 21109004001,
      "COUNTRY_TERRITORY" : 2276,
      "REGION" : 20235,
      "STR_REGION" : "North Rhine-Westphalia",
      "Clicks" : 0,
      "Country" : "GER",
      "Language" : "DE",
      "Category" : "BusinessIndustrial",
      "CampaignName" : "GER_DE_04_P_BusinessIndustrial_LTG000_oo_oo_S_A#544",
      "AdNetworkType2" : "Google Search",
      "Date" : "2016-12-25",
      "DayOfWeek" : "Sunday    ",
      "Device" : "PC",
      "MonthOfYear" : "December       ",
      "Keyword" : null,
      "GoogleAdPosition" : 2.7,
      "MatchType" : null,
      "Impressions" : 12
    }, {
      "ID_GRUPO" : 36874384791,
      "ID_KEYWORD" : 21109004001,
      "COUNTRY_TERRITORY" : 2276,
      "REGION" : 20235,
      "STR_REGION" : "North Rhine-Westphalia",
      "Clicks" : 0,
      "Country" : "GER",
      "Language" : "DE",
      "Category" : "BusinessIndustrial",
      "CampaignName" : "GER_DE_04_P_BusinessIndustrial_LTG000_oo_oo_S_A#544",
      "AdNetworkType2" : "Google Search",
      "Date" : "2016-12-25",
      "DayOfWeek" : "Sunday    ",
      "Device" : "PC",
      "MonthOfYear" : "December       ",
      "Keyword" : null,
      "GoogleAdPosition" : 2.7,
      "MatchType" : null,
      "Impressions" : 18
    }, {
      "ID_GRUPO" : 36874384791,
      "ID_KEYWORD" : 21109004001,
      "COUNTRY_TERRITORY" : 2276,
      "REGION" : 20235,
      "STR_REGION" : "North Rhine-Westphalia",
      "Clicks" : 0,
      "Country" : "GER",
      "Language" : "DE",
      "Category" : "BusinessIndustrial",
      "CampaignName" : "GER_DE_04_P_BusinessIndustrial_LTG000_oo_oo_S_A#544",
      "AdNetworkType2" : "Google Search",
      "Date" : "2016-12-25",
      "DayOfWeek" : "Sunday    ",
      "Device" : "PC",
      "MonthOfYear" : "December       ",
      "Keyword" : null,
      "GoogleAdPosition" : 2.7,
      "MatchType" : null,
      "Impressions" : 4
    }, {
      "ID_GRUPO" : 36874384791,
      "ID_KEYWORD" : 21109004001,
      "COUNTRY_TERRITORY" : 2276,
      "REGION" : 20235,
      "STR_REGION" : "North Rhine-Westphalia",
      "Clicks" : 0,
      "Country" : "GER",
      "Language" : "DE",
      "Category" : "BusinessIndustrial",
      "CampaignName" : "GER_DE_04_P_BusinessIndustrial_LTG000_oo_oo_S_A#544",
      "AdNetworkType2" : "Google Search",
      "Date" : "2016-12-25",
      "DayOfWeek" : "Sunday    ",
      "Device" : "PC",
      "MonthOfYear" : "December       ",
      "Keyword" : null,
      "GoogleAdPosition" : 2.7,
      "MatchType" : null,
      "Impressions" : 2
    }, {
      "ID_GRUPO" : 36874384791,
      "ID_KEYWORD" : 21109004001,
      "COUNTRY_TERRITORY" : 2276,
      "REGION" : 20235,
      "STR_REGION" : "North Rhine-Westphalia",
      "Clicks" : 0,
      "Country" : "GER",
      "Language" : "DE",
      "Category" : "BusinessIndustrial",
      "CampaignName" : "GER_DE_04_P_BusinessIndustrial_LTG000_oo_oo_S_A#544",
      "AdNetworkType2" : "Google Search",
      "Date" : "2016-12-25",
      "DayOfWeek" : "Sunday    ",
      "Device" : "PC",
      "MonthOfYear" : "December       ",
      "Keyword" : null,
      "GoogleAdPosition" : 2.7,
      "MatchType" : null,
      "Impressions" : 20
    }, {
      "ID_GRUPO" : 36874384791,
      "ID_KEYWORD" : 21109004001,
      "COUNTRY_TERRITORY" : 2276,
      "REGION" : 20235,
      "STR_REGION" : "North Rhine-Westphalia",
      "Clicks" : 0,
      "Country" : "GER",
      "Language" : "DE",
      "Category" : "BusinessIndustrial",
      "CampaignName" : "GER_DE_04_P_BusinessIndustrial_LTG000_oo_oo_S_A#544",
      "AdNetworkType2" : "Google Search",
      "Date" : "2016-12-25",
      "DayOfWeek" : "Sunday    ",
      "Device" : "PC",
      "MonthOfYear" : "December       ",
      "Keyword" : null,
      "GoogleAdPosition" : 2.7,
      "MatchType" : null,
      "Impressions" : 4
    }, {
      "ID_GRUPO" : 36874384791,
      "ID_KEYWORD" : 21109004001,
      "COUNTRY_TERRITORY" : 2276,
      "REGION" : 20235,
      "STR_REGION" : "North Rhine-Westphalia",
      "Clicks" : 0,
      "Country" : "GER",
      "Language" : "DE",
      "Category" : "BusinessIndustrial",
      "CampaignName" : "GER_DE_04_P_BusinessIndustrial_LTG000_oo_oo_S_A#544",
      "AdNetworkType2" : "Google Search",
      "Date" : "2016-12-25",
      "DayOfWeek" : "Sunday    ",
      "Device" : "PC",
      "MonthOfYear" : "December       ",
      "Keyword" : null,
      "GoogleAdPosition" : 2.7,
      "MatchType" : null,
      "Impressions" : 6
    }, {
      "ID_GRUPO" : 36874384791,
      "ID_KEYWORD" : 21109004001,
      "COUNTRY_TERRITORY" : 2276,
      "REGION" : 20235,
      "STR_REGION" : "North Rhine-Westphalia",
      "Clicks" : 0,
      "Country" : "GER",
      "Language" : "DE",
      "Category" : "BusinessIndustrial",
      "CampaignName" : "GER_DE_04_P_BusinessIndustrial_LTG000_oo_oo_S_A#544",
      "AdNetworkType2" : "Google Search",
      "Date" : "2016-12-25",
      "DayOfWeek" : "Sunday    ",
      "Device" : "PC",
      "MonthOfYear" : "December       ",
      "Keyword" : null,
      "GoogleAdPosition" : 2.7,
      "MatchType" : null,
      "Impressions" : 6
    }, {
      "ID_GRUPO" : 36874384791,
      "ID_KEYWORD" : 21109004001,
      "COUNTRY_TERRITORY" : 2276,
      "REGION" : 20235,
      "STR_REGION" : "North Rhine-Westphalia",
      "Clicks" : 0,
      "Country" : "GER",
      "Language" : "DE",
      "Category" : "BusinessIndustrial",
      "CampaignName" : "GER_DE_04_P_BusinessIndustrial_LTG000_oo_oo_S_A#544",
      "AdNetworkType2" : "Google Search",
      "Date" : "2016-12-25",
      "DayOfWeek" : "Sunday    ",
      "Device" : "PC",
      "MonthOfYear" : "December       ",
      "Keyword" : null,
      "GoogleAdPosition" : 2.7,
      "MatchType" : null,
      "Impressions" : 2
    }, {
      "ID_GRUPO" : 36874384791,
      "ID_KEYWORD" : 21109004001,
      "COUNTRY_TERRITORY" : 2276,
      "REGION" : 20235,
      "STR_REGION" : "North Rhine-Westphalia",
      "Clicks" : 0,
      "Country" : "GER",
      "Language" : "DE",
      "Category" : "BusinessIndustrial",
      "CampaignName" : "GER_DE_04_P_BusinessIndustrial_LTG000_oo_oo_S_A#544",
      "AdNetworkType2" : "Google Search",
      "Date" : "2016-12-25",
      "DayOfWeek" : "Sunday    ",
      "Device" : "PC",
      "MonthOfYear" : "December       ",
      "Keyword" : null,
      "GoogleAdPosition" : 2.7,
      "MatchType" : null,
      "Impressions" : 4
    }, {
      "ID_GRUPO" : 36874384791,
      "ID_KEYWORD" : 21109004001,
      "COUNTRY_TERRITORY" : 2276,
      "REGION" : 20235,
      "STR_REGION" : "North Rhine-Westphalia",
      "Clicks" : 0,
      "Country" : "GER",
      "Language" : "DE",
      "Category" : "BusinessIndustrial",
      "CampaignName" : "GER_DE_04_P_BusinessIndustrial_LTG000_oo_oo_S_A#544",
      "AdNetworkType2" : "Google Search",
      "Date" : "2016-12-25",
      "DayOfWeek" : "Sunday    ",
      "Device" : "PC",
      "MonthOfYear" : "December       ",
      "Keyword" : null,
      "GoogleAdPosition" : 2.7,
      "MatchType" : null,
      "Impressions" : 6
    }, {
      "ID_GRUPO" : 36874384791,
      "ID_KEYWORD" : 21109004001,
      "COUNTRY_TERRITORY" : 2276,
      "REGION" : 20235,
      "STR_REGION" : "North Rhine-Westphalia",
      "Clicks" : 0,
      "Country" : "GER",
      "Language" : "DE",
      "Category" : "BusinessIndustrial",
      "CampaignName" : "GER_DE_04_P_BusinessIndustrial_LTG000_oo_oo_S_A#544",
      "AdNetworkType2" : "Google Search",
      "Date" : "2016-12-25",
      "DayOfWeek" : "Sunday    ",
      "Device" : "PC",
      "MonthOfYear" : "December       ",
      "Keyword" : null,
      "GoogleAdPosition" : 2.7,
      "MatchType" : null,
      "Impressions" : 2
    }, {
      "ID_GRUPO" : 36874384791,
      "ID_KEYWORD" : 21109004001,
      "COUNTRY_TERRITORY" : 2276,
      "REGION" : 20235,
      "STR_REGION" : "North Rhine-Westphalia",
      "Clicks" : 0,
      "Country" : "GER",
      "Language" : "DE",
      "Category" : "BusinessIndustrial",
      "CampaignName" : "GER_DE_04_P_BusinessIndustrial_LTG000_oo_oo_S_A#544",
      "AdNetworkType2" : "Google Search",
      "Date" : "2016-12-25",
      "DayOfWeek" : "Sunday    ",
      "Device" : "PC",
      "MonthOfYear" : "December       ",
      "Keyword" : null,
      "GoogleAdPosition" : 2.7,
      "MatchType" : null,
      "Impressions" : 2
    }, {
      "ID_GRUPO" : 36874384791,
      "ID_KEYWORD" : 21109004001,
      "COUNTRY_TERRITORY" : 2276,
      "REGION" : 20235,
      "STR_REGION" : "North Rhine-Westphalia",
      "Clicks" : 0,
      "Country" : "GER",
      "Language" : "DE",
      "Category" : "BusinessIndustrial",
      "CampaignName" : "GER_DE_04_P_BusinessIndustrial_LTG000_oo_oo_S_A#544",
      "AdNetworkType2" : "Google Search",
      "Date" : "2016-12-25",
      "DayOfWeek" : "Sunday    ",
      "Device" : "PC",
      "MonthOfYear" : "December       ",
      "Keyword" : null,
      "GoogleAdPosition" : 2.7,
      "MatchType" : null,
      "Impressions" : 4
    }, {
      "ID_GRUPO" : 36874384791,
      "ID_KEYWORD" : 21109004001,
      "COUNTRY_TERRITORY" : 2276,
      "REGION" : 20235,
      "STR_REGION" : "North Rhine-Westphalia",
      "Clicks" : 0,
      "Country" : "GER",
      "Language" : "DE",
      "Category" : "BusinessIndustrial",
      "CampaignName" : "GER_DE_04_P_BusinessIndustrial_LTG000_oo_oo_S_A#544",
      "AdNetworkType2" : "Google Search",
      "Date" : "2016-12-25",
      "DayOfWeek" : "Sunday    ",
      "Device" : "PC",
      "MonthOfYear" : "December       ",
      "Keyword" : null,
      "GoogleAdPosition" : 2.7,
      "MatchType" : null,
      "Impressions" : 2
    }, {
      "ID_GRUPO" : 36874384791,
      "ID_KEYWORD" : 21109004001,
      "COUNTRY_TERRITORY" : 2276,
      "REGION" : 20235,
      "STR_REGION" : "North Rhine-Westphalia",
      "Clicks" : 0,
      "Country" : "GER",
      "Language" : "DE",
      "Category" : "BusinessIndustrial",
      "CampaignName" : "GER_DE_04_P_BusinessIndustrial_LTG000_oo_oo_S_A#544",
      "AdNetworkType2" : "Google Search",
      "Date" : "2016-12-25",
      "DayOfWeek" : "Sunday    ",
      "Device" : "PC",
      "MonthOfYear" : "December       ",
      "Keyword" : null,
      "GoogleAdPosition" : 2.7,
      "MatchType" : null,
      "Impressions" : 10
    }, {
      "ID_GRUPO" : 36874384791,
      "ID_KEYWORD" : 21109004001,
      "COUNTRY_TERRITORY" : 2276,
      "REGION" : 20235,
      "STR_REGION" : "North Rhine-Westphalia",
      "Clicks" : 0,
      "Country" : "GER",
      "Language" : "DE",
      "Category" : "BusinessIndustrial",
      "CampaignName" : "GER_DE_04_P_BusinessIndustrial_LTG000_oo_oo_S_A#544",
      "AdNetworkType2" : "Google Search",
      "Date" : "2016-12-25",
      "DayOfWeek" : "Sunday    ",
      "Device" : "PC",
      "MonthOfYear" : "December       ",
      "Keyword" : null,
      "GoogleAdPosition" : 2.7,
      "MatchType" : null,
      "Impressions" : 4
    }, {
      "ID_GRUPO" : 36874384791,
      "ID_KEYWORD" : 21109004001,
      "COUNTRY_TERRITORY" : 2276,
      "REGION" : 20235,
      "STR_REGION" : "North Rhine-Westphalia",
      "Clicks" : 0,
      "Country" : "GER",
      "Language" : "DE",
      "Category" : "BusinessIndustrial",
      "CampaignName" : "GER_DE_04_P_BusinessIndustrial_LTG000_oo_oo_S_A#544",
      "AdNetworkType2" : "Google Search",
      "Date" : "2016-12-25",
      "DayOfWeek" : "Sunday    ",
      "Device" : "PC",
      "MonthOfYear" : "December       ",
      "Keyword" : null,
      "GoogleAdPosition" : 2.7,
      "MatchType" : null,
      "Impressions" : 10
    }, {
      "ID_GRUPO" : 36874384791,
      "ID_KEYWORD" : 21109004001,
      "COUNTRY_TERRITORY" : 2276,
      "REGION" : 20235,
      "STR_REGION" : "North Rhine-Westphalia",
      "Clicks" : 0,
      "Country" : "GER",
      "Language" : "DE",
      "Category" : "BusinessIndustrial",
      "CampaignName" : "GER_DE_04_P_BusinessIndustrial_LTG000_oo_oo_S_A#544",
      "AdNetworkType2" : "Google Search",
      "Date" : "2016-12-25",
      "DayOfWeek" : "Sunday    ",
      "Device" : "PC",
      "MonthOfYear" : "December       ",
      "Keyword" : null,
      "GoogleAdPosition" : 2.7,
      "MatchType" : null,
      "Impressions" : 32
    }, {
      "ID_GRUPO" : 36874384791,
      "ID_KEYWORD" : 21109004001,
      "COUNTRY_TERRITORY" : 2276,
      "REGION" : 20235,
      "STR_REGION" : "North Rhine-Westphalia",
      "Clicks" : 0,
      "Country" : "GER",
      "Language" : "DE",
      "Category" : "BusinessIndustrial",
      "CampaignName" : "GER_DE_04_P_BusinessIndustrial_LTG000_oo_oo_S_A#544",
      "AdNetworkType2" : "Google Search",
      "Date" : "2016-12-25",
      "DayOfWeek" : "Sunday    ",
      "Device" : "PC",
      "MonthOfYear" : "December       ",
      "Keyword" : null,
      "GoogleAdPosition" : 2.7,
      "MatchType" : null,
      "Impressions" : 2
    }, {
      "ID_GRUPO" : 36874384791,
      "ID_KEYWORD" : 21109004001,
      "COUNTRY_TERRITORY" : 2276,
      "REGION" : 20235,
      "STR_REGION" : "North Rhine-Westphalia",
      "Clicks" : 0,
      "Country" : "GER",
      "Language" : "DE",
      "Category" : "BusinessIndustrial",
      "CampaignName" : "GER_DE_04_P_BusinessIndustrial_LTG000_oo_oo_S_A#544",
      "AdNetworkType2" : "Google Search",
      "Date" : "2016-12-25",
      "DayOfWeek" : "Sunday    ",
      "Device" : "PC",
      "MonthOfYear" : "December       ",
      "Keyword" : null,
      "GoogleAdPosition" : 2.7,
      "MatchType" : null,
      "Impressions" : 2
    }, {
      "ID_GRUPO" : 36874384791,
      "ID_KEYWORD" : 21109004001,
      "COUNTRY_TERRITORY" : 2276,
      "REGION" : 20235,
      "STR_REGION" : "North Rhine-Westphalia",
      "Clicks" : 0,
      "Country" : "GER",
      "Language" : "DE",
      "Category" : "BusinessIndustrial",
      "CampaignName" : "GER_DE_04_P_BusinessIndustrial_LTG000_oo_oo_S_A#544",
      "AdNetworkType2" : "Google Search",
      "Date" : "2016-12-25",
      "DayOfWeek" : "Sunday    ",
      "Device" : "PC",
      "MonthOfYear" : "December       ",
      "Keyword" : null,
      "GoogleAdPosition" : 2.7,
      "MatchType" : null,
      "Impressions" : 52
    }, {
      "ID_GRUPO" : 36874384791,
      "ID_KEYWORD" : 22418326791,
      "COUNTRY_TERRITORY" : 2276,
      "REGION" : 20235,
      "STR_REGION" : "North Rhine-Westphalia",
      "Clicks" : 0,
      "Country" : "GER",
      "Language" : "DE",
      "Category" : "BusinessIndustrial",
      "CampaignName" : "GER_DE_04_P_BusinessIndustrial_LTG000_oo_oo_S_A#544",
      "AdNetworkType2" : "Search Partners",
      "Date" : "2016-12-25",
      "DayOfWeek" : "Sunday    ",
      "Device" : "PC",
      "MonthOfYear" : "December       ",
      "Keyword" : null,
      "GoogleAdPosition" : 7.0,
      "MatchType" : null,
      "Impressions" : 2
    }, {
      "ID_GRUPO" : 36874384791,
      "ID_KEYWORD" : 23084339816,
      "COUNTRY_TERRITORY" : 2276,
      "REGION" : 20235,
      "STR_REGION" : "North Rhine-Westphalia",
      "Clicks" : 0,
      "Country" : "GER",
      "Language" : "DE",
      "Category" : "BusinessIndustrial",
      "CampaignName" : "GER_DE_04_P_BusinessIndustrial_LTG000_oo_oo_S_A#544",
      "AdNetworkType2" : "Search Partners",
      "Date" : "2016-12-25",
      "DayOfWeek" : "Sunday    ",
      "Device" : "PC",
      "MonthOfYear" : "December       ",
      "Keyword" : null,
      "GoogleAdPosition" : 7.0,
      "MatchType" : null,
      "Impressions" : 1
    }, {
      "ID_GRUPO" : 36874384791,
      "ID_KEYWORD" : 24041402184,
      "COUNTRY_TERRITORY" : 2276,
      "REGION" : 20235,
      "STR_REGION" : "North Rhine-Westphalia",
      "Clicks" : 0,
      "Country" : "GER",
      "Language" : "DE",
      "Category" : "BusinessIndustrial",
      "CampaignName" : "GER_DE_04_P_BusinessIndustrial_LTG000_oo_oo_S_A#544",
      "AdNetworkType2" : "Search Partners",
      "Date" : "2016-12-25",
      "DayOfWeek" : "Sunday    ",
      "Device" : "PC",
      "MonthOfYear" : "December       ",
      "Keyword" : null,
      "GoogleAdPosition" : 5.3,
      "MatchType" : null,
      "Impressions" : 4
    }, {
      "ID_GRUPO" : 36874384791,
      "ID_KEYWORD" : 24468470168,
      "COUNTRY_TERRITORY" : 2276,
      "REGION" : 20235,
      "STR_REGION" : "North Rhine-Westphalia",
      "Clicks" : 0,
      "Country" : "GER",
      "Language" : "DE",
      "Category" : "BusinessIndustrial",
      "CampaignName" : "GER_DE_04_P_BusinessIndustrial_LTG000_oo_oo_S_A#544",
      "AdNetworkType2" : "Search Partners",
      "Date" : "2016-12-25",
      "DayOfWeek" : "Sunday    ",
      "Device" : "PC",
      "MonthOfYear" : "December       ",
      "Keyword" : null,
      "GoogleAdPosition" : 7.0,
      "MatchType" : null,
      "Impressions" : 1
    }, {
      "ID_GRUPO" : 36874384791,
      "ID_KEYWORD" : 25090955938,
      "COUNTRY_TERRITORY" : 2276,
      "REGION" : 20235,
      "STR_REGION" : "North Rhine-Westphalia",
      "Clicks" : 0,
      "Country" : "GER",
      "Language" : "DE",
      "Category" : "BusinessIndustrial",
      "CampaignName" : "GER_DE_04_P_BusinessIndustrial_LTG000_oo_oo_S_A#544",
      "AdNetworkType2" : "Search Partners",
      "Date" : "2016-12-25",
      "DayOfWeek" : "Sunday    ",
      "Device" : "PC",
      "MonthOfYear" : "December       ",
      "Keyword" : null,
      "GoogleAdPosition" : 6.0,
      "MatchType" : null,
      "Impressions" : 1
    }, {
      "ID_GRUPO" : 36874384791,
      "ID_KEYWORD" : 25294729400,
      "COUNTRY_TERRITORY" : 2276,
      "REGION" : 20235,
      "STR_REGION" : "North Rhine-Westphalia",
      "Clicks" : 0,
      "Country" : "GER",
      "Language" : "DE",
      "Category" : "BusinessIndustrial",
      "CampaignName" : "GER_DE_04_P_BusinessIndustrial_LTG000_oo_oo_S_A#544",
      "AdNetworkType2" : "Search Partners",
      "Date" : "2016-12-25",
      "DayOfWeek" : "Sunday    ",
      "Device" : "PC",
      "MonthOfYear" : "December       ",
      "Keyword" : null,
      "GoogleAdPosition" : 4.8,
      "MatchType" : null,
      "Impressions" : 2
    }, {
      "ID_GRUPO" : 36874384791,
      "ID_KEYWORD" : 25294729400,
      "COUNTRY_TERRITORY" : 2276,
      "REGION" : 20235,
      "STR_REGION" : "North Rhine-Westphalia",
      "Clicks" : 0,
      "Country" : "GER",
      "Language" : "DE",
      "Category" : "BusinessIndustrial",
      "CampaignName" : "GER_DE_04_P_BusinessIndustrial_LTG000_oo_oo_S_A#544",
      "AdNetworkType2" : "Search Partners",
      "Date" : "2016-12-25",
      "DayOfWeek" : "Sunday    ",
      "Device" : "PC",
      "MonthOfYear" : "December       ",
      "Keyword" : null,
      "GoogleAdPosition" : 4.8,
      "MatchType" : null,
      "Impressions" : 6
    }, {
      "ID_GRUPO" : 36874384791,
      "ID_KEYWORD" : 25294729400,
      "COUNTRY_TERRITORY" : 2276,
      "REGION" : 20235,
      "STR_REGION" : "North Rhine-Westphalia",
      "Clicks" : 0,
      "Country" : "GER",
      "Language" : "DE",
      "Category" : "BusinessIndustrial",
      "CampaignName" : "GER_DE_04_P_BusinessIndustrial_LTG000_oo_oo_S_A#544",
      "AdNetworkType2" : "Search Partners",
      "Date" : "2016-12-25",
      "DayOfWeek" : "Sunday    ",
      "Device" : "PC",
      "MonthOfYear" : "December       ",
      "Keyword" : null,
      "GoogleAdPosition" : 4.8,
      "MatchType" : null,
      "Impressions" : 6
    }, {
      "ID_GRUPO" : 36874384791,
      "ID_KEYWORD" : 25294729400,
      "COUNTRY_TERRITORY" : 2276,
      "REGION" : 20235,
      "STR_REGION" : "North Rhine-Westphalia",
      "Clicks" : 0,
      "Country" : "GER",
      "Language" : "DE",
      "Category" : "BusinessIndustrial",
      "CampaignName" : "GER_DE_04_P_BusinessIndustrial_LTG000_oo_oo_S_A#544",
      "AdNetworkType2" : "Search Partners",
      "Date" : "2016-12-25",
      "DayOfWeek" : "Sunday    ",
      "Device" : "PC",
      "MonthOfYear" : "December       ",
      "Keyword" : null,
      "GoogleAdPosition" : 4.8,
      "MatchType" : null,
      "Impressions" : 2
    }, {
      "ID_GRUPO" : 36874384791,
      "ID_KEYWORD" : 25294729400,
      "COUNTRY_TERRITORY" : 2276,
      "REGION" : 20235,
      "STR_REGION" : "North Rhine-Westphalia",
      "Clicks" : 0,
      "Country" : "GER",
      "Language" : "DE",
      "Category" : "BusinessIndustrial",
      "CampaignName" : "GER_DE_04_P_BusinessIndustrial_LTG000_oo_oo_S_A#544",
      "AdNetworkType2" : "Search Partners",
      "Date" : "2016-12-25",
      "DayOfWeek" : "Sunday    ",
      "Device" : "PC",
      "MonthOfYear" : "December       ",
      "Keyword" : null,
      "GoogleAdPosition" : 4.8,
      "MatchType" : null,
      "Impressions" : 1
    }, {
      "ID_GRUPO" : 36874384791,
      "ID_KEYWORD" : 25294729400,
      "COUNTRY_TERRITORY" : 2276,
      "REGION" : 20235,
      "STR_REGION" : "North Rhine-Westphalia",
      "Clicks" : 0,
      "Country" : "GER",
      "Language" : "DE",
      "Category" : "BusinessIndustrial",
      "CampaignName" : "GER_DE_04_P_BusinessIndustrial_LTG000_oo_oo_S_A#544",
      "AdNetworkType2" : "Search Partners",
      "Date" : "2016-12-25",
      "DayOfWeek" : "Sunday    ",
      "Device" : "PC",
      "MonthOfYear" : "December       ",
      "Keyword" : null,
      "GoogleAdPosition" : 4.8,
      "MatchType" : null,
      "Impressions" : 1
    }, {
      "ID_GRUPO" : 36874384791,
      "ID_KEYWORD" : 25294729400,
      "COUNTRY_TERRITORY" : 2276,
      "REGION" : 20235,
      "STR_REGION" : "North Rhine-Westphalia",
      "Clicks" : 0,
      "Country" : "GER",
      "Language" : "DE",
      "Category" : "BusinessIndustrial",
      "CampaignName" : "GER_DE_04_P_BusinessIndustrial_LTG000_oo_oo_S_A#544",
      "AdNetworkType2" : "Search Partners",
      "Date" : "2016-12-25",
      "DayOfWeek" : "Sunday    ",
      "Device" : "PC",
      "MonthOfYear" : "December       ",
      "Keyword" : null,
      "GoogleAdPosition" : 4.8,
      "MatchType" : null,
      "Impressions" : 2
    }, {
      "ID_GRUPO" : 36874384791,
      "ID_KEYWORD" : 25294729400,
      "COUNTRY_TERRITORY" : 2276,
      "REGION" : 20235,
      "STR_REGION" : "North Rhine-Westphalia",
      "Clicks" : 0,
      "Country" : "GER",
      "Language" : "DE",
      "Category" : "BusinessIndustrial",
      "CampaignName" : "GER_DE_04_P_BusinessIndustrial_LTG000_oo_oo_S_A#544",
      "AdNetworkType2" : "Search Partners",
      "Date" : "2016-12-25",
      "DayOfWeek" : "Sunday    ",
      "Device" : "PC",
      "MonthOfYear" : "December       ",
      "Keyword" : null,
      "GoogleAdPosition" : 4.8,
      "MatchType" : null,
      "Impressions" : 2
    }, {
      "ID_GRUPO" : 36874384791,
      "ID_KEYWORD" : 25294729400,
      "COUNTRY_TERRITORY" : 2276,
      "REGION" : 20235,
      "STR_REGION" : "North Rhine-Westphalia",
      "Clicks" : 0,
      "Country" : "GER",
      "Language" : "DE",
      "Category" : "BusinessIndustrial",
      "CampaignName" : "GER_DE_04_P_BusinessIndustrial_LTG000_oo_oo_S_A#544",
      "AdNetworkType2" : "Search Partners",
      "Date" : "2016-12-25",
      "DayOfWeek" : "Sunday    ",
      "Device" : "PC",
      "MonthOfYear" : "December       ",
      "Keyword" : null,
      "GoogleAdPosition" : 4.8,
      "MatchType" : null,
      "Impressions" : 1
    }, {
      "ID_GRUPO" : 36874384791,
      "ID_KEYWORD" : 25294729400,
      "COUNTRY_TERRITORY" : 2276,
      "REGION" : 20235,
      "STR_REGION" : "North Rhine-Westphalia",
      "Clicks" : 0,
      "Country" : "GER",
      "Language" : "DE",
      "Category" : "BusinessIndustrial",
      "CampaignName" : "GER_DE_04_P_BusinessIndustrial_LTG000_oo_oo_S_A#544",
      "AdNetworkType2" : "Search Partners",
      "Date" : "2016-12-25",
      "DayOfWeek" : "Sunday    ",
      "Device" : "PC",
      "MonthOfYear" : "December       ",
      "Keyword" : null,
      "GoogleAdPosition" : 4.8,
      "MatchType" : null,
      "Impressions" : 1
    }, {
      "ID_GRUPO" : 36874384791,
      "ID_KEYWORD" : 25384304481,
      "COUNTRY_TERRITORY" : 2276,
      "REGION" : 20235,
      "STR_REGION" : "North Rhine-Westphalia",
      "Clicks" : 0,
      "Country" : "GER",
      "Language" : "DE",
      "Category" : "BusinessIndustrial",
      "CampaignName" : "GER_DE_04_P_BusinessIndustrial_LTG000_oo_oo_S_A#544",
      "AdNetworkType2" : "Search Partners",
      "Date" : "2016-12-25",
      "DayOfWeek" : "Sunday    ",
      "Device" : "PC",
      "MonthOfYear" : "December       ",
      "Keyword" : null,
      "GoogleAdPosition" : 2.5,
      "MatchType" : null,
      "Impressions" : 2
    }, {
      "ID_GRUPO" : 36874384791,
      "ID_KEYWORD" : 26441263286,
      "COUNTRY_TERRITORY" : 2276,
      "REGION" : 20235,
      "STR_REGION" : "North Rhine-Westphalia",
      "Clicks" : 0,
      "Country" : "GER",
      "Language" : "DE",
      "Category" : "BusinessIndustrial",
      "CampaignName" : "GER_DE_04_P_BusinessIndustrial_LTG000_oo_oo_S_A#544",
      "AdNetworkType2" : "Search Partners",
      "Date" : "2016-12-25",
      "DayOfWeek" : "Sunday    ",
      "Device" : "PC",
      "MonthOfYear" : "December       ",
      "Keyword" : null,
      "GoogleAdPosition" : 5.0,
      "MatchType" : null,
      "Impressions" : 3
    }, {
      "ID_GRUPO" : 36874384791,
      "ID_KEYWORD" : 26814560883,
      "COUNTRY_TERRITORY" : 2276,
      "REGION" : 20235,
      "STR_REGION" : "North Rhine-Westphalia",
      "Clicks" : 0,
      "Country" : "GER",
      "Language" : "DE",
      "Category" : "BusinessIndustrial",
      "CampaignName" : "GER_DE_04_P_BusinessIndustrial_LTG000_oo_oo_S_A#544",
      "AdNetworkType2" : "Search Partners",
      "Date" : "2016-12-25",
      "DayOfWeek" : "Sunday    ",
      "Device" : "PC",
      "MonthOfYear" : "December       ",
      "Keyword" : null,
      "GoogleAdPosition" : 6.3,
      "MatchType" : null,
      "Impressions" : 3
    }, {
      "ID_GRUPO" : 36874384791,
      "ID_KEYWORD" : 26817879198,
      "COUNTRY_TERRITORY" : 2276,
      "REGION" : 20235,
      "STR_REGION" : "North Rhine-Westphalia",
      "Clicks" : 0,
      "Country" : "GER",
      "Language" : "DE",
      "Category" : "BusinessIndustrial",
      "CampaignName" : "GER_DE_04_P_BusinessIndustrial_LTG000_oo_oo_S_A#544",
      "AdNetworkType2" : "Google Search",
      "Date" : "2016-12-25",
      "DayOfWeek" : "Sunday    ",
      "Device" : "PC",
      "MonthOfYear" : "December       ",
      "Keyword" : null,
      "GoogleAdPosition" : 3.0,
      "MatchType" : null,
      "Impressions" : 1
    }, {
      "ID_GRUPO" : 36874384791,
      "ID_KEYWORD" : 27029938536,
      "COUNTRY_TERRITORY" : 2276,
      "REGION" : 20235,
      "STR_REGION" : "North Rhine-Westphalia",
      "Clicks" : 0,
      "Country" : "GER",
      "Language" : "DE",
      "Category" : "BusinessIndustrial",
      "CampaignName" : "GER_DE_04_P_BusinessIndustrial_LTG000_oo_oo_S_A#544",
      "AdNetworkType2" : "Google Search",
      "Date" : "2016-12-25",
      "DayOfWeek" : "Sunday    ",
      "Device" : "PC",
      "MonthOfYear" : "December       ",
      "Keyword" : null,
      "GoogleAdPosition" : 3.0,
      "MatchType" : null,
      "Impressions" : 1
    }, {
      "ID_GRUPO" : 36874384791,
      "ID_KEYWORD" : 27213264305,
      "COUNTRY_TERRITORY" : 2276,
      "REGION" : 20235,
      "STR_REGION" : "North Rhine-Westphalia",
      "Clicks" : 0,
      "Country" : "GER",
      "Language" : "DE",
      "Category" : "BusinessIndustrial",
      "CampaignName" : "GER_DE_04_P_BusinessIndustrial_LTG000_oo_oo_S_A#544",
      "AdNetworkType2" : "Search Partners",
      "Date" : "2016-12-25",
      "DayOfWeek" : "Sunday    ",
      "Device" : "PC",
      "MonthOfYear" : "December       ",
      "Keyword" : null,
      "GoogleAdPosition" : 6.0,
      "MatchType" : null,
      "Impressions" : 1
    }, {
      "ID_GRUPO" : 36874384791,
      "ID_KEYWORD" : 27213264305,
      "COUNTRY_TERRITORY" : 2276,
      "REGION" : 20235,
      "STR_REGION" : "North Rhine-Westphalia",
      "Clicks" : 0,
      "Country" : "GER",
      "Language" : "DE",
      "Category" : "BusinessIndustrial",
      "CampaignName" : "GER_DE_04_P_BusinessIndustrial_LTG000_oo_oo_S_A#544",
      "AdNetworkType2" : "Search Partners",
      "Date" : "2016-12-25",
      "DayOfWeek" : "Sunday    ",
      "Device" : "PC",
      "MonthOfYear" : "December       ",
      "Keyword" : null,
      "GoogleAdPosition" : 6.0,
      "MatchType" : null,
      "Impressions" : 1
    }, {
      "ID_GRUPO" : 36874384791,
      "ID_KEYWORD" : 27217771265,
      "COUNTRY_TERRITORY" : 2276,
      "REGION" : 20235,
      "STR_REGION" : "North Rhine-Westphalia",
      "Clicks" : 0,
      "Country" : "GER",
      "Language" : "DE",
      "Category" : "BusinessIndustrial",
      "CampaignName" : "GER_DE_04_P_BusinessIndustrial_LTG000_oo_oo_S_A#544",
      "AdNetworkType2" : "Search Partners",
      "Date" : "2016-12-25",
      "DayOfWeek" : "Sunday    ",
      "Device" : "PC",
      "MonthOfYear" : "December       ",
      "Keyword" : null,
      "GoogleAdPosition" : 7.0,
      "MatchType" : null,
      "Impressions" : 1
    }, {
      "ID_GRUPO" : 36874384791,
      "ID_KEYWORD" : 27257134872,
      "COUNTRY_TERRITORY" : 2276,
      "REGION" : 20235,
      "STR_REGION" : "North Rhine-Westphalia",
      "Clicks" : 0,
      "Country" : "GER",
      "Language" : "DE",
      "Category" : "BusinessIndustrial",
      "CampaignName" : "GER_DE_04_P_BusinessIndustrial_LTG000_oo_oo_S_A#544",
      "AdNetworkType2" : "Search Partners",
      "Date" : "2016-12-25",
      "DayOfWeek" : "Sunday    ",
      "Device" : "PC",
      "MonthOfYear" : "December       ",
      "Keyword" : null,
      "GoogleAdPosition" : 5.8,
      "MatchType" : null,
      "Impressions" : 4
    }, {
      "ID_GRUPO" : 36874384791,
      "ID_KEYWORD" : 27450339539,
      "COUNTRY_TERRITORY" : 2276,
      "REGION" : 20235,
      "STR_REGION" : "North Rhine-Westphalia",
      "Clicks" : 0,
      "Country" : "GER",
      "Language" : "DE",
      "Category" : "BusinessIndustrial",
      "CampaignName" : "GER_DE_04_P_BusinessIndustrial_LTG000_oo_oo_S_A#544",
      "AdNetworkType2" : "Google Search",
      "Date" : "2016-12-25",
      "DayOfWeek" : "Sunday    ",
      "Device" : "PC",
      "MonthOfYear" : "December       ",
      "Keyword" : null,
      "GoogleAdPosition" : 2.3,
      "MatchType" : null,
      "Impressions" : 2
    }, {
      "ID_GRUPO" : 36874384791,
      "ID_KEYWORD" : 27450339539,
      "COUNTRY_TERRITORY" : 2276,
      "REGION" : 20235,
      "STR_REGION" : "North Rhine-Westphalia",
      "Clicks" : 0,
      "Country" : "GER",
      "Language" : "DE",
      "Category" : "BusinessIndustrial",
      "CampaignName" : "GER_DE_04_P_BusinessIndustrial_LTG000_oo_oo_S_A#544",
      "AdNetworkType2" : "Google Search",
      "Date" : "2016-12-25",
      "DayOfWeek" : "Sunday    ",
      "Device" : "PC",
      "MonthOfYear" : "December       ",
      "Keyword" : null,
      "GoogleAdPosition" : 2.3,
      "MatchType" : null,
      "Impressions" : 2
    }, {
      "ID_GRUPO" : 36874384791,
      "ID_KEYWORD" : 27450339539,
      "COUNTRY_TERRITORY" : 2276,
      "REGION" : 20235,
      "STR_REGION" : "North Rhine-Westphalia",
      "Clicks" : 0,
      "Country" : "GER",
      "Language" : "DE",
      "Category" : "BusinessIndustrial",
      "CampaignName" : "GER_DE_04_P_BusinessIndustrial_LTG000_oo_oo_S_A#544",
      "AdNetworkType2" : "Google Search",
      "Date" : "2016-12-25",
      "DayOfWeek" : "Sunday    ",
      "Device" : "PC",
      "MonthOfYear" : "December       ",
      "Keyword" : null,
      "GoogleAdPosition" : 2.3,
      "MatchType" : null,
      "Impressions" : 2
    }, {
      "ID_GRUPO" : 36874384791,
      "ID_KEYWORD" : 27450339539,
      "COUNTRY_TERRITORY" : 2276,
      "REGION" : 20235,
      "STR_REGION" : "North Rhine-Westphalia",
      "Clicks" : 0,
      "Country" : "GER",
      "Language" : "DE",
      "Category" : "BusinessIndustrial",
      "CampaignName" : "GER_DE_04_P_BusinessIndustrial_LTG000_oo_oo_S_A#544",
      "AdNetworkType2" : "Google Search",
      "Date" : "2016-12-25",
      "DayOfWeek" : "Sunday    ",
      "Device" : "PC",
      "MonthOfYear" : "December       ",
      "Keyword" : null,
      "GoogleAdPosition" : 2.3,
      "MatchType" : null,
      "Impressions" : 4
    } ]
}
